sumire/__about__.py
sumire/__init__.py
sumire/resources/model_card/gensim/README.md
sumire/resources/model_card/gensim/cc.ja.300.json
sumire/resources/model_card/gensim/chive/chive-1.0-mc5.json
sumire/resources/model_card/gensim/chive/chive-1.1-mc15.json
sumire/resources/model_card/gensim/chive/chive-1.1-mc30.json
sumire/resources/model_card/gensim/chive/chive-1.1-mc5.json
sumire/resources/model_card/gensim/chive/chive-1.1-mc90.json
sumire/resources/model_card/gensim/chive/chive-1.2-mc15.json
sumire/resources/model_card/gensim/chive/chive-1.2-mc30.json
sumire/resources/model_card/gensim/chive/chive-1.2-mc5.json
sumire/resources/model_card/gensim/chive/chive-1.2-mc90.json
sumire/resources/model_card/gensim/cl-tohoku_jawiki_vector/20180402/jawiki.all_vectors.100d.json
sumire/resources/model_card/gensim/cl-tohoku_jawiki_vector/20180402/jawiki.all_vectors.200d.json
sumire/resources/model_card/gensim/cl-tohoku_jawiki_vector/20180402/jawiki.all_vectors.300d.json
sumire/resources/model_card/gensim/cl-tohoku_jawiki_vector/20180402/jawiki.entity_vectors.100d.json
sumire/resources/model_card/gensim/cl-tohoku_jawiki_vector/20180402/jawiki.entity_vectors.200d.json
sumire/resources/model_card/gensim/cl-tohoku_jawiki_vector/20180402/jawiki.entity_vectors.300d.json
sumire/resources/model_card/gensim/cl-tohoku_jawiki_vector/20180402/jawiki.word_vectors.100d.json
sumire/resources/model_card/gensim/cl-tohoku_jawiki_vector/20180402/jawiki.word_vectors.200d.json
sumire/resources/model_card/gensim/cl-tohoku_jawiki_vector/20180402/jawiki.word_vectors.300d.json
sumire/resources/model_card/gensim/cl-tohoku_jawiki_vector/20181001/jawiki.all_vectors.100d.json
sumire/resources/model_card/gensim/cl-tohoku_jawiki_vector/20181001/jawiki.all_vectors.200d.json
sumire/resources/model_card/gensim/cl-tohoku_jawiki_vector/20181001/jawiki.all_vectors.300d.json
sumire/resources/model_card/gensim/cl-tohoku_jawiki_vector/20181001/jawiki.entity_vectors.100d.json
sumire-1.0.2.dist-info/METADATA
sumire-1.0.2.dist-info/WHEEL
sumire-1.0.2.dist-info/licenses/LICENSE
sumire-1.0.2.dist-info/RECORD
