Metadata-Version: 2.1
Name: sumire
Version: 1.0.2
Summary: Scikit-learn compatible Japanese text vectorizer for CPU-based Japanese natural language processing.
Project-URL: Documentation, https://reiven-c-t.github.io/sumire/
Project-URL: Issues, https://github.com/reiven-c-t/sumire/issues
Project-URL: Source, https://github.com/reiven-c-t/sumire
Author-email: "a.k.a.underfirst" <a.k.a.underfirst@mail.com>
License-Expression: MIT
License-File: LICENSE
Keywords: Japanese,NLP,Natural Language Processing,Scikit-learn,Tokenizer
Classifier: Development Status :: 4 - Beta
Classifier: Programming Language :: Python
Classifier: Programming Language :: Python :: 3.9
Classifier: Programming Language :: Python :: 3.10
Classifier: Programming Language :: Python :: 3.11
Classifier: Programming Language :: Python :: Implementation :: CPython
Classifier: Programming Language :: Python :: Implementation :: PyPy
Requires-Python: >=3.9
Requires-Dist: fugashi
Requires-Dist: gensim>=4.2
Requires-Dist: ginza>=3
Requires-Dist: inflection
Requires-Dist: ipadic
Requires-Dist: ja-ginza>=3
Requires-Dist: loguru
Requires-Dist: mecab-python3
Requires-Dist: protobuf
Requires-Dist: pyknp>=0.4
Requires-Dist: scikit-learn>=0.17
Requires-Dist: sentencepiece>=0.1.90
Requires-Dist: sudachidict-full
Requires-Dist: sudachipy>=0.2
Requires-Dist: torch
Requires-Dist: transformers
Requires-Dist: unidic
Requires-Dist: unidic-lite
